xdo/__init__.py
xdo/_xdo.py
xdo-0.5.dist-info/COPYING
xdo-0.5.dist-info/METADATA
xdo-0.5.dist-info/WHEEL
xdo-0.5.dist-info/top_level.txt
xdo-0.5.dist-info/RECORD
